dataairlock/__init__.py
dataairlock/app.py
dataairlock/cli.py
dataairlock/document_pseudonymizer.py
dataairlock/folder_scanner.py
dataairlock/hybrid_detector.py
dataairlock/llm_client.py
dataairlock/profile.py
dataairlock/pseudonymizer.py
dataairlock/tui.py
dataairlock-0.4.0.dist-info/licenses/LICENSE
dataairlock-0.4.0.dist-info/METADATA
dataairlock-0.4.0.dist-info/WHEEL
dataairlock-0.4.0.dist-info/entry_points.txt
dataairlock-0.4.0.dist-info/top_level.txt
dataairlock-0.4.0.dist-info/RECORD
