Metadata-Version: 2.4
Name: dataairlock
Version: 0.4.0
Summary: 個人情報を仮名化してクラウドLLMに安全に渡すためのツール
Author-email: akira0907 <akira0907@users.noreply.github.com>
License-Expression: MIT
Project-URL: Homepage, https://github.com/akira0907/dataairlock
Project-URL: Repository, https://github.com/akira0907/dataairlock
Project-URL: Issues, https://github.com/akira0907/dataairlock/issues
Keywords: pseudonymization,privacy,pii,llm,data-protection,gdpr,japanese
Classifier: Development Status :: 4 - Beta
Classifier: Environment :: Console
Classifier: Intended Audience :: Developers
Classifier: Intended Audience :: Science/Research
Classifier: Natural Language :: Japanese
Classifier: Operating System :: OS Independent
Classifier: Programming Language :: Python :: 3
Classifier: Programming Language :: Python :: 3.10
Classifier: Programming Language :: Python :: 3.11
Classifier: Programming Language :: Python :: 3.12
Classifier: Topic :: Security
Classifier: Topic :: Text Processing
Classifier: Typing :: Typed
Requires-Python: >=3.10
License-File: LICENSE
Requires-Dist: pandas>=2.0.0
Requires-Dist: cryptography>=42.0.0
Requires-Dist: openpyxl>=3.1.0
Requires-Dist: typer[all]>=0.9.0
Requires-Dist: rich>=13.0.0
Requires-Dist: python-docx>=1.1.0
Requires-Dist: python-pptx>=0.6.23
Requires-Dist: questionary>=2.0.0
Provides-Extra: dev
Requires-Dist: pytest>=8.0.0; extra == "dev"
Requires-Dist: build>=1.0.0; extra == "dev"
Requires-Dist: twine>=5.0.0; extra == "dev"
Provides-Extra: streamlit
Requires-Dist: streamlit>=1.30.0; extra == "streamlit"
Provides-Extra: ollama
Requires-Dist: ollama>=0.1.0; extra == "ollama"
Provides-Extra: all
Requires-Dist: dataairlock[ollama,streamlit]; extra == "all"
Dynamic: license-file
